README.md
mdstat-influx.py
setup.py
mdstat_influx/__init__.py
mdstat_influx/mdstat_influx.py
mdstat_influx.egg-info/PKG-INFO
mdstat_influx.egg-info/SOURCES.txt
mdstat_influx.egg-info/dependency_links.txt
mdstat_influx.egg-info/requires.txt
mdstat_influx.egg-info/top_level.txt