Metadata-Version: 2.1
Name: mdstat-influx
Version: 0.1.0
Summary: Read mdstat and output to line format
Home-page: https://gitlab.com/rveach/mdstat-influx
Author: Ryan Veach
Author-email: rveach@gmail.com
License: MIT
Download-URL: https://gitlab.com/rveach/mdstat-influx/-/archive/master/mdstat-influx-master.tar.gz
Keywords: mdstat,mdadm,influxdb
Platform: UNKNOWN
Classifier: Development Status :: 3 - Alpha
Classifier: Intended Audience :: Developers
Classifier: License :: OSI Approved :: MIT License
Classifier: Natural Language :: English
Classifier: Operating System :: POSIX :: Linux
Classifier: Programming Language :: Python :: 3
Classifier: Topic :: Software Development :: Libraries
Requires-Python: >=3.5
